{"cameraMode":{"drawMode":0,"name":"Shaded","section":"Shading Mode"},"sceneLighting":true,"audioPlay":false,"sceneViewState":{"m_AlwaysRefresh":false,"showFog":true,"showSkybox":true,"showFlares":true,"showImageEffects":true,"showParticleSystems":true,"showVisualEffectGraphs":true,"m_FxEnabled":true},"in2DMode":false,"pivot":{"x":-3.267152786254883,"y":-3.4699182510375978,"z":-7.871913909912109},"rotation":{"x":-0.28379398584365847,"y":0.17479825019836427,"z":-0.052697326987981799,"w":-0.9413520097732544},"size":11.602090835571289,"orthographic":false}